Trabalho tp/display.v
module display (entrada, a, b, c, d, e, f , g);
    input wire [4:0] entrada;
    output reg a, b, c, d, e, f, g;
    //output reg [6:0] sete_segmentos;
    always @(*) begin
        case (entrada)
            5'b00000:
                {a, b, c, d, e, f, g} = 7'b1111001;
            5'b00001:
                {a, b, c, d, e, f, g} = 7'b0111110;
            5'b00010:
                {a, b, c, d, e, f, g} = 7'b0110011;
            5'b00011:
                {a, b, c, d, e, f, g} = 7'b0000101;
            5'b00100:
                {a, b, c, d, e, f, g} = 7'b0001111;
            5'b00101:
                {a, b, c, d, e, f, g} = 7'b1101101;
            5'b00110:
                {a, b, c, d, e, f, g} = 7'b1111110;
            5'b00111:
                {a, b, c, d, e, f, g} = 7'b1001110;
            5'b01000:
                {a, b, c, d, e, f, g} = 7'b1111111;
            5'b01001:
                {a, b, c, d, e, f, g} = 7'b1111011;
            5'b01010:
                {a, b, c, d, e, f, g} = 7'b1110011;
            5'b01011:
                {a, b, c, d, e, f, g} = 7'b1101101;
            5'b01100:
                {a, b, c, d, e, f, g} = 7'b1100111;
            5'b01101:
                {a, b, c, d, e, f, g} = 7'b0010101;
            5'b01110:
                {a, b, c, d, e, f, g} = 7'b0110000;
            5'b01111:
                {a, b, c, d, e, f, g} = 7'b1110111;
            5'b10000:
                {a, b, c, d, e, f, g} = 7'b0001110;
            5'b10001:
                {a, b, c, d, e, f, g} = 7'b1011111;
            5'b10010:
                {a, b, c, d, e, f, g} = 7'b1111011;
            5'b10011:
                {a, b, c, d, e, f, g}  = 7'b1000111;
            default:
                {a, b, c, d, e, f, g} = 7'b0000000;
        endcase
    end

endmodule

Trabalho tp/display_tb.v
`timescale 1ps/1ps
`include "display.v"
module display_tb;
    reg [4:0] entrada;
    wire a, b, c, d, e, f, g;
    display display_tb (entrada, a, b, c, d, e, f, g);

    initial begin
        $dumpfile("display_tb.vcd");
        $dumpvars(0, display_tb);
        $monitor("entrada = %b  abcdefg = %b%b%b%b%b%b%b", entrada, a, b, c, d, e, f, g);
        entrada = 5'b00000;
        #10 entrada = 5'b00001;
        #10 entrada = 5'b00010;
        #10 entrada = 5'b00011;
        #10 entrada = 5'b00100;
        #10 entrada = 5'b00101;
        #10 entrada = 5'b00110;
        #10 entrada = 5'b00111;
        #10 entrada = 5'b01000;
        #10 entrada = 5'b01001;
        #10 entrada = 5'b01010;
        #10 entrada = 5'b01011;
        #10 entrada = 5'b01100;
        #10 entrada = 5'b01101;
        #10 entrada = 5'b01110;
        #10 entrada = 5'b01111;
        #10 entrada = 5'b10000;
        #10 entrada = 5'b10001;
        #10 entrada = 5'b10010;
        #10 entrada = 5'b10011;
        #10 entrada = 5'b10100;
        #10 entrada = 5'b10101;
        #10 entrada = 5'b10110;
        #10 entrada = 5'b10111;
        #10 entrada = 5'b11000;
        #10 entrada = 5'b11001;
        #10 entrada = 5'b11010;
        #10 entrada = 5'b11011;
        #10 entrada = 5'b11100;
        #10 entrada = 5'b11101;
        #10 entrada = 5'b11110;
        #10 entrada = 5'b11111;
        #10 $finish;
    end
endmodule

Trabalho tp/display_tb.vcd
$date
	Sat Feb 19 18:39:27 2022
$end
$version
	Icarus Verilog
$end
$timescale
	1ps
$end
$scope module display_tb $end
$scope module display_tb $end
$var wire 5 ! entrada [4:0] $end
$var reg 1 " a $end
$var reg 1 # b $end
$var reg 1 $ c $end
$var reg 1 % d $end
$var reg 1 & e $end
$var reg 1 ' f $end
$var reg 1 ( g $end
$upscope $end
$upscope $end
$enddefinitions $end
#0
$dumpvars
1(
0'
0&
1%
1$
1#
1"
b0 !
$end
#10
0"
1&
1'
0(
b1 !
#20
0%
0&
1(
b10 !
#30
0#
0$
1&
0'
b11 !
#40
1%
1'
b100 !
#50
1"
1#
0'
b101 !
#60
1$
1'
0(
b110 !
#70
0#
0$
b111 !
#80
1#
1$
1(
b1000 !
#90
0&
b1001 !
#100
0%
b1010 !
#110
0$
1%
1&
0'
b1011 !
#120
0%
1'
b1100 !
#130
0"
0#
1$
0'
b1101 !
#140
1#
0&
0(
b1110 !
#150
1"
1&
1'
1(
b1111 !
#160
0"
0#
0$
1%
0(
b10000 !
#170
1"
1$
1(
b10001 !
#180
1#
0&
b10010 !
#190
0#
0$
0%
1&
b10011 !
#200
0"
0&
0'
0(
b10100 !
#210
b10101 !
#220
b10110 !
#230
b10111 !
#240
b11000 !
#250
b11001 !
#260
b11010 !
#270
b11011 !
#280
b11100 !
#290
b11101 !
#300
b11110 !
#310
b11111 !
